rio_xpw/__init__.py
rio_xpw/access.py
rio_xpw/attribute.py
rio_xpw-0.1.dist-info/LICENSE
rio_xpw-0.1.dist-info/METADATA
rio_xpw-0.1.dist-info/WHEEL
rio_xpw-0.1.dist-info/top_level.txt
rio_xpw-0.1.dist-info/zip-safe
rio_xpw-0.1.dist-info/RECORD
