Metadata-Version: 2.1
Name: rio-xpw
Version: 0.1
Summary: Rio access control based on xpw
Home-page: https://github.com/bondbox/rio-xpw/
Author: Mingzhe Zou
Author-email: zoumingzhe@outlook.com
License: GPLv2
Project-URL: Source Code, https://github.com/bondbox/rio-xpw/
Project-URL: Bug Tracker, https://github.com/bondbox/rio-xpw/issues
Project-URL: Documentation, https://github.com/bondbox/rio-xpw/
Keywords: auth,access,authentication
Platform: any
Classifier: Programming Language :: Python
Classifier: Programming Language :: Python :: 3
Requires-Python: >=3.10
License-File: LICENSE
Requires-Dist: xpw >=0.15.1
Requires-Dist: rio-ui
